tatapov/__init__.py
tatapov/annealing_data.py
tatapov/utils.py
tatapov/version.py
tatapov-0.2.4.dist-info/licenses/LICENSE
tatapov-0.2.4.dist-info/METADATA
tatapov-0.2.4.dist-info/WHEEL
tatapov-0.2.4.dist-info/top_level.txt
tatapov-0.2.4.dist-info/RECORD
