Metadata-Version: 2.4
Name: tatapov
Version: 0.2.4
Summary: Tools for DNA overhang misannealing data.
Author: Zulko
License-Expression: MIT
Project-URL: Homepage, https://github.com/Edinburgh-Genome-Foundry/tatapov
Keywords: overhang,golden gate,DNA,annealing,mismatch
License-File: LICENSE
Requires-Dist: pandas
Requires-Dist: appdirs
Requires-Dist: openpyxl
Dynamic: license-file
